Workbook

Sheet Assumptions
A1: Financial Model Assumptions
A2: Category | B2: Bear Case | C2: Base Case | D2: Bull Case
A3: Monthly New Customers | B3: 20 | C3: 25 | D3: 30
A4: Customer Acquisition Cost (CAC) | B4: 150 | C4: 125 | D4: 100
A5: ARPU (Monthly Recurring Revenue per Customer) | B5: 18 | C5: 20 | D5: 22
A6: Monthly Churn Rate | B6: 0.08 | C6: 0.05 | D6: 0.03
A7: Variable Cost per Customer | B7: 2 | C7: 2 | D7: 2
A8: Sales & Marketing Spend (Fixed Monthly) | B8: 1500 | C8: 1500 | D8: 1500
A9: Product Development (Fixed Monthly) | B9: 3000 | C9: 3000 | D9: 3000
A10: General & Administrative (Fixed Monthly) | B10: 1000 | C10: 1000 | D10: 1000

Sheet Unit Economics
A1: Unit Economics (Monthly)
A2: Metric | B2: Bear Case | C2: Base Case | D2: Bull Case
A3: ARPU | B3: ='Assumptions'!B5 | C3: ='Assumptions'!C5 | D3: ='Assumptions'!D5
A4: CAC | B4: ='Assumptions'!B4 | C4: ='Assumptions'!C4 | D4: ='Assumptions'!D4
A5: Monthly Churn Rate | B5: ='Assumptions'!B6 | C5: ='Assumptions'!C6 | D5: ='Assumptions'!D6
A6: Variable Cost per Customer | B6: ='Assumptions'!B7 | C6: ='Assumptions'!C7 | D6: ='Assumptions'!D7
A7: Gross Margin per Customer | B7: =B3-B6 | C7: =C3-C6 | D7: =D3-D6
A8: LTV (Lifetime Value) | B8: =B7/B5 | C8: =C7/C5 | D8: =D7/D5
A9: LTV:CAC Ratio | B9: =B8/B4 | C9: =C8/C4 | D9: =D8/D4
A10: Payback Period (Months) | B10: =B4/B7 | C10: =C4/C7 | D10: =D4/D7

Sheet P&L
A1: Profit & Loss (Monthly)
A2: Metric | B2: Bear Case | C2: Base Case | D2: Bull Case
A3: New Customers | B3: ='Assumptions'!B3 | C3: ='Assumptions'!C3 | D3: ='Assumptions'!D3
A4: Total Customers (Month 1) | B4: =B3 | C4: =C3 | D4: =D3
A5: Revenue | B5: =B4*'Assumptions'!B5 | C5: =C4*'Assumptions'!C5 | D5: =D4*'Assumptions'!D5
A6: COGS | B6: =B4*'Assumptions'!B7 | C6: =C4*'Assumptions'!C7 | D6: =D4*'Assumptions'!D7
A7: Gross Profit | B7: =B5-B6 | C7: =C5-C6 | D7: =D5-D6
A8: Operating Expenses
A9: Sales & Marketing | B9: ='Assumptions'!B8 | C9: ='Assumptions'!C8 | D9: ='Assumptions'!D8
A10: Product Development | B10: ='Assumptions'!B9 | C10: ='Assumptions'!C9 | D10: ='Assumptions'!D9
A11: General & Administrative | B11: ='Assumptions'!B10 | C11: ='Assumptions'!C10 | D11: ='Assumptions'!D10
A12: Total Operating Expenses | B12: =SUM(B9:B11) | C12: =SUM(C9:C11) | D12: =SUM(D9:D11)
A13: Net Income | B13: =B7-B12 | C13: =C7-C12 | D13: =D7-D12

Sheet Sensitivity Analysis
A1: Sensitivity Analysis (Net Income Impact)
A2: Variable | B2: Base Case Net Income | C2: -20% Change | D2: Net Income (-20%) | E2: +20% Change | F2: Net Income (+20%)
A3: Monthly New Customers | B3: =P&L!C13 | C3: ='Assumptions'!C3*0.8 | D3: =(P&L!C5/P&L!C4)*C3 - (P&L!C6/P&L!C4)*C3 - P&L!C12 | E3: ='Assumptions'!C3*1.2 | F3: =(P&L!C5/P&L!C4)*E3 - (P&L!C6/P&L!C4)*E3 - P&L!C12
A4: ARPU | B4: =P&L!C13 | C4: ='Assumptions'!C5*0.8 | D4: =P&L!C4*C4 - P&L!C6 - P&L!C12 | E4: ='Assumptions'!C5*1.2 | F4: =P&L!C4*E4 - P&L!C6 - P&L!C12
A5: Monthly Churn Rate | B5: =P&L!C13 | C5: ='Assumptions'!C6*1.2 | D5: =(P&L!C5/P&L!C4)*(P&L!C4*(1-C5)) - (P&L!C6/P&L!C4)*(P&L!C4*(1-C5)) - P&L!C12 | E5: ='Assumptions'!C6*0.8 | F5: =(P&L!C5/P&L!C4)*(P&L!C4*(1-E5)) - (P&L!C6/P&L!C4)*(P&L!C4*(1-E5)) - P&L!C12
A6: CAC | B6: =P&L!C13 | C6: ='Assumptions'!C4*1.2 | D6: =P&L!C7 - P&L!C9 - P&L!C10 - P&L!C11 | E6: ='Assumptions'!C4*0.8 | F6: =P&L!C7 - P&L!C9 - P&L!C10 - P&L!C11
